LICENSE
MANIFEST.in
README.md
setup.cfg
setup.py
gameprices/__init__.py
gameprices/offer.py
gameprices/price.py
gameprices/shop.py
gameprices.egg-info/PKG-INFO
gameprices.egg-info/SOURCES.txt
gameprices.egg-info/dependency_links.txt
gameprices.egg-info/entry_points.txt
gameprices.egg-info/top_level.txt
gameprices/cli/__init__.py
gameprices/cli/cli.py
gameprices/cli/mailalert.py
gameprices/shops/__init__.py
gameprices/shops/eshop.py
gameprices/shops/psn.py
gameprices/test/__init__.py
gameprices/test/commons.py
gameprices/test/test_cli.py
gameprices/test/test_dealmailalert.py
gameprices/test/test_eshop.py
gameprices/test/test_psn.py
gameprices/test/test_psnpricealert.py
gameprices/test/test_utils.py
gameprices/utils/__init__.py
gameprices/utils/utils.py