Metadata-Version: 2.1
Name: gameprices
Version: 1.3.3
Summary: An interface for the undocumented Sony PlayStation Store PSN and Nintendo Eshop Apis
Home-page: https://github.com/snipem/psnprices
Author: Matthias Kuech
Author-email: post@matthias-kuech.de
License: GPL2
Download-URL: https://github.com/snipem/psnprices/archive/1.0.tar.gz
Keywords: playstation,eshop,store,prices
Platform: UNKNOWN
License-File: LICENSE
